my_ui_booking/__init__.py
my_ui_booking/booking.py
my_ui_booking/change_currency.py
my_ui_booking/change_language.py
my_ui_booking/constants.py
my_ui_booking/utils.py
my_ui_booking-0.1.dist-info/METADATA
my_ui_booking-0.1.dist-info/WHEEL
my_ui_booking-0.1.dist-info/top_level.txt
my_ui_booking-0.1.dist-info/RECORD
