Metadata-Version: 2.1
Name: my-ui-booking
Version: 0.1
Summary: 1st release of my package
Author: Arijit Das
